tap_vimeo/__init__.py
tap_vimeo/__main__.py
tap_vimeo/client.py
tap_vimeo/schemas/__init__.py
tap_vimeo/streams.py
tap_vimeo/tap.py
oviond_tap_vimeo-0.0.3.dist-info/METADATA
oviond_tap_vimeo-0.0.3.dist-info/WHEEL
oviond_tap_vimeo-0.0.3.dist-info/entry_points.txt
oviond_tap_vimeo-0.0.3.dist-info/RECORD
